auviewer-1.0.1.dist-info/WHEEL
auviewer-1.0.1.dist-info/RECORD
auviewer-1.0.1.dist-info/entry_points.txt
auviewer-1.0.1.dist-info/top_level.txt
auviewer-1.0.1.dist-info/LICENSE
auviewer-1.0.1.dist-info/METADATA
auviewer/patternset.py
auviewer/tools.py
auviewer/api.py
auviewer/downsampleset.py
auviewer/series.py
auviewer/project.py
auviewer/file.py
auviewer/cylib.cpython-38-x86_64-linux-gnu.so
auviewer/serve.py
auviewer/rawdata.py
auviewer/shared.py
auviewer/models.py
auviewer/__init__.py
auviewer/config.py
auviewer/static/www/fonts/materialdesignicons-webfont.ttf
auviewer/static/www/fonts/materialdesignicons-webfont.eot
auviewer/static/www/fonts/fontawesome-webfont.ttf
auviewer/static/www/fonts/materialdesignicons-webfont.woff
auviewer/static/www/fonts/materialdesignicons-webfont.woff2
auviewer/static/www/fonts/fontawesome-webfont.woff2
auviewer/static/www/css/app.css
auviewer/static/www/css/third-party/bootstrap-select.min.css
auviewer/static/www/css/third-party/bootstrap.min.css
auviewer/static/www/css/third-party/datatables.min.css
auviewer/static/www/css/third-party/dygraph.css
auviewer/static/www/css/third-party/webix.min.css
auviewer/static/www/css/third-party/materialdesignicons.min.css
auviewer/static/www/css/third-party/font-awesome.min.css
auviewer/static/www/css/third-party/fonts/webixfa-webfont.woff
auviewer/static/www/css/third-party/fonts/Lato-Bold.ttf
auviewer/static/www/css/third-party/fonts/webixfa-webfont.woff2
auviewer/static/www/css/third-party/fonts/PTS-webfont.woff
auviewer/static/www/css/third-party/fonts/font-license.txt
auviewer/static/www/css/third-party/fonts/Roboto-Regular-webfont.woff2
auviewer/static/www/css/third-party/fonts/webixmdi-webfont.woff2
auviewer/static/www/css/third-party/fonts/Roboto-Medium-webfont.woff2
auviewer/static/www/css/third-party/fonts/PTS-bold.woff
auviewer/static/www/css/third-party/fonts/Roboto-Medium-webfont.woff
auviewer/static/www/css/third-party/fonts/Lato-Regular.ttf
auviewer/static/www/css/third-party/fonts/Lato-Light.ttf
auviewer/static/www/css/third-party/fonts/webixmdi-webfont.woff
auviewer/static/www/css/third-party/fonts/Roboto-Regular-webfont.woff
