Metadata-Version: 2.1
Name: auviewer
Version: 1.0.1
Summary: A general-purpose time series exploration & annotation tool.
Home-page: https://github.com/autonlab/auviewer
Author: Gus Welter
Author-email: gwelter@cmu.edu
Maintainer: Gus Welter
Maintainer-email: gwelter@cmu.edu
License: MIT
Platform: UNKNOWN
Classifier: Operating System :: OS Independent
Classifier: Intended Audience :: Science/Research
Classifier: Programming Language :: Python :: 3.7
Classifier: Programming Language :: Python :: 3.8
Classifier: Topic :: Scientific/Engineering
Requires-Python: >=3.7
Requires-Dist: audata
Requires-Dist: bcrypt
Requires-Dist: email-validator
Requires-Dist: flask (==2.3.3)
Requires-Dist: flask-login
Requires-Dist: flask-mail
Requires-Dist: flask-sqlalchemy
Requires-Dist: flask-wtf
Requires-Dist: htmlmin
Requires-Dist: jsbeautifier
Requires-Dist: numpy (>=1.19.5)
Requires-Dist: pandas
Requires-Dist: passlib
Requires-Dist: psutil
Requires-Dist: pycryptodome
Requires-Dist: simplejson
Requires-Dist: sqlalchemy (>=2.0)
